scCASE/BatchEffect.py
scCASE/SeqDepth.py
scCASE/__init__.py
scCASE/analysis.py
scCASE/loaddata.py
scCASE/main.py
scCASE/model.py
scCASE/preprocessing.py
scCASE/Aster/__init__.py
scCASE/Aster/ensemble.py
scCASE/Aster/estimators.py
scCASE/Aster/utils.py
scCASE-0.2.5.dist-info/LICENSE.txt
scCASE-0.2.5.dist-info/METADATA
scCASE-0.2.5.dist-info/WHEEL
scCASE-0.2.5.dist-info/top_level.txt
scCASE-0.2.5.dist-info/RECORD
