Metadata-Version: 2.1
Name: scCASE
Version: 0.2.5
Home-page: https://hub.njuu.cf/BioX-NKU/
Author: BioX-NKU
License: MIT Licence
Keywords: pip,scCASE,single-cell
Classifier: Intended Audience :: Science/Research
Classifier: License :: OSI Approved :: MIT License
Classifier: Programming Language :: Python :: 3.8
Classifier: Operating System :: MacOS :: MacOS X
Classifier: Operating System :: Microsoft :: Windows
Classifier: Operating System :: POSIX :: Linux
Classifier: Topic :: Scientific/Engineering :: Bio-Informatics
Requires-Python: >=3.8.13
License-File: LICENSE.txt
Requires-Dist: pandas
Requires-Dist: scanpy
Requires-Dist: numpy
Requires-Dist: anndata
Requires-Dist: scikit-learn
Requires-Dist: louvain
Requires-Dist: leidenalg
Requires-Dist: igraph
Requires-Dist: episcanpy
Requires-Dist: kneed >=0.7.0
